{
  "project_info": {
    "project_number": "572322137024",
    "project_id": "sistema-gestion-3b225",
    "storage_bucket": "sistema-gestion-3b225.firebasestorage.app"
  },
  "client": [
    {
      "client_info": {
        "mobilesdk_app_id": "1:572322137024:android:77d6ca4d0b58e8ace43e25",
        "android_client_info": {
          "package_name": "com.wala.tienda"
        }
      },
      "oauth_client": [
        {
          "client_id": "572322137024-0bl118c7mnuglq3fbnbdlhv5kg36dp9a.apps.googleusercontent.com",
          "client_type": 3
        }
      ],
      "api_key": [
        {
          "current_key": "AIzaSyCFfyvfJ0IOXRd7DA0EmDQN3CtAx-nz59M"
        }
      ],
      "services": {
        "appinvite_service": {
          "other_platform_oauth_client": [
            {
              "client_id": "572322137024-0bl118c7mnuglq3fbnbdlhv5kg36dp9a.apps.googleusercontent.com",
              "client_type": 3
            }
          ]
        }
      }
    }
  ],
  "configuration_version": "1"
}